IntellijIdeaZhongwenWendang/README.md
IntellijIdeaZhongwenWendang/__init__.py
IntellijIdeaZhongwenWendang/__main__.py
IntellijIdeaZhongwenWendang/file.epub
IntellijIdeaZhongwenWendang/index.html
IntellijIdeaZhongwenWendang/css/__init__.py
IntellijIdeaZhongwenWendang/css/annotations.css
IntellijIdeaZhongwenWendang/css/main.css
IntellijIdeaZhongwenWendang/css/normalize.css
IntellijIdeaZhongwenWendang/css/popup.css
IntellijIdeaZhongwenWendang/font/__init__.py
IntellijIdeaZhongwenWendang/font/fontello.eot
IntellijIdeaZhongwenWendang/font/fontello.svg
IntellijIdeaZhongwenWendang/font/fontello.ttf
IntellijIdeaZhongwenWendang/font/fontello.woff
IntellijIdeaZhongwenWendang/img/__init__.py
IntellijIdeaZhongwenWendang/img/annotator-glyph-sprite.png
IntellijIdeaZhongwenWendang/img/annotator-icon-sprite.png
IntellijIdeaZhongwenWendang/img/apple-touch-icon.png
IntellijIdeaZhongwenWendang/img/cancelfullscreen.png
IntellijIdeaZhongwenWendang/img/close.png
IntellijIdeaZhongwenWendang/img/fullscreen.png
IntellijIdeaZhongwenWendang/img/loader.gif
IntellijIdeaZhongwenWendang/img/menu-icon.png
IntellijIdeaZhongwenWendang/img/save.png
IntellijIdeaZhongwenWendang/img/saved.png
IntellijIdeaZhongwenWendang/img/settings-s.png
IntellijIdeaZhongwenWendang/img/settings.png
IntellijIdeaZhongwenWendang/img/star.png
IntellijIdeaZhongwenWendang/js/__init__.py
IntellijIdeaZhongwenWendang/js/epub.js
IntellijIdeaZhongwenWendang/js/epub.min.js
IntellijIdeaZhongwenWendang/js/epub.min.map
IntellijIdeaZhongwenWendang/js/hooks.min.js
IntellijIdeaZhongwenWendang/js/hooks.min.map
IntellijIdeaZhongwenWendang/js/reader.js
IntellijIdeaZhongwenWendang/js/reader.js.map
IntellijIdeaZhongwenWendang/js/reader.min.js
IntellijIdeaZhongwenWendang/js/reader.min.map
IntellijIdeaZhongwenWendang/js/hooks/__init__.py
IntellijIdeaZhongwenWendang/js/hooks/extensions/__init__.py
IntellijIdeaZhongwenWendang/js/hooks/extensions/highlight.js
IntellijIdeaZhongwenWendang/js/libs/__init__.py
intellij_idea_zhongwen_wendang-2024.3.4.0.dist-info/METADATA
intellij_idea_zhongwen_wendang-2024.3.4.0.dist-info/WHEEL
intellij_idea_zhongwen_wendang-2024.3.4.0.dist-info/entry_points.txt
intellij_idea_zhongwen_wendang-2024.3.4.0.dist-info/top_level.txt
intellij_idea_zhongwen_wendang-2024.3.4.0.dist-info/RECORD
